comto_dadata/__init__.py
comto_dadata/address.py
comto_dadata/company.py
comto_dadata/handbook.py
comto_dadata/parse.py
comto_dadata/profile.py
comto_dadata-4.1.2.dist-info/LICENSE
comto_dadata-4.1.2.dist-info/METADATA
comto_dadata-4.1.2.dist-info/WHEEL
comto_dadata-4.1.2.dist-info/top_level.txt
comto_dadata-4.1.2.dist-info/RECORD
