Metadata-Version: 2.1
Name: comto-dadata
Version: 4.1.2
Summary: Работа с сервисом "dadata.ru": запросы, обработка, итд
Home-page: http://commercito.ru
Author: commercito
Author-email: commercito@gmail.com
License: UNKNOWN
Platform: UNKNOWN
Classifier: Programming Language :: Python :: 3.8
Classifier: License :: OSI Approved :: MIT License
Classifier: Operating System :: OS Independent
Classifier: Programming Language :: Python
Classifier: Natural Language :: Russian
Classifier: Intended Audience :: Developers
Classifier: License :: Freely Distributable
Classifier: Topic :: Utilities
Requires-Python: >=3.8
